CHANGES.txt
MANIFEST.in
README.txt
setup.cfg
setup.py
js/__init__.py
js.jquery_tooltip.egg-info/PKG-INFO
js.jquery_tooltip.egg-info/SOURCES.txt
js.jquery_tooltip.egg-info/dependency_links.txt
js.jquery_tooltip.egg-info/entry_points.txt
js.jquery_tooltip.egg-info/namespace_packages.txt
js.jquery_tooltip.egg-info/not-zip-safe
js.jquery_tooltip.egg-info/requires.txt
js.jquery_tooltip.egg-info/top_level.txt
js/jquery_tooltip/__init__.py
js/jquery_tooltip/test_jquery_tooltip.txt
js/jquery_tooltip/resources/jquery.tooltip.css
js/jquery_tooltip/resources/jquery.tooltip.js
js/jquery_tooltip/resources/jquery.tooltip.min.js
js/jquery_tooltip/resources/jquery.tooltip.pack.js