Metadata-Version: 1.0
Name: js.jquery-tooltip
Version: 1.3
Summary: fanstatic jQuery tooltip.
Home-page: UNKNOWN
Author: Fanstatic Developers
Author-email: fanstatic@googlegroups.com
License: BSD
Platform: UNKNOWN
